Metadata-Version: 2.1
Name: oierspace
Version: 1.0.0
Summary: An Python SDK for OIer Space
Home-page: https://github.com/jin-dan/pyoierspace
Author: Qin Yuzhen
Author-email: 1@jin-dan.site
License: MIT License
Platform: UNKNOWN
License-File: LICENSE
